LICENSE
chipscopy/__init__.py
chipscopy/_cli/__init__.py
chipscopy/_cli/_chipscopy.py
chipscopy/_cli/example_delivery.py
chipscopy/api/__init__.py
chipscopy/api/_detail/__init__.py
chipscopy/api/_detail/debug_core.py
chipscopy/api/_detail/ltx.py
chipscopy/api/_detail/property.py
chipscopy/api/_detail/trace.py
chipscopy/api/cable.py
chipscopy/api/containers.py
chipscopy/api/ddr/__init__.py
chipscopy/api/ddr/ddr.py
chipscopy/api/device/__init__.py
chipscopy/api/device/client_program_log.py
chipscopy/api/device/device.py
chipscopy/api/device/device_scanner.py
chipscopy/api/device/device_spec.py
chipscopy/api/device/device_util.py
chipscopy/api/hbm/__init__.py
chipscopy/api/hbm/hbm.py
chipscopy/api/hbm/hbmmc.py
chipscopy/api/ibert/__init__.py
chipscopy/api/ibert/aliases.py
chipscopy/api/ibert/eye_scan/__init__.py
chipscopy/api/ibert/eye_scan/manager.py
chipscopy/api/ibert/eye_scan/params.py
chipscopy/api/ibert/eye_scan/plotter.py
chipscopy/api/ibert/gt.py
chipscopy/api/ibert/gt_common.py
chipscopy/api/ibert/gt_group.py
chipscopy/api/ibert/ibert.py
chipscopy/api/ibert/link/__init__.py
chipscopy/api/ibert/link/group.py
chipscopy/api/ibert/link/manager.py
chipscopy/api/ibert/pll.py
chipscopy/api/ibert/rx.py
chipscopy/api/ibert/serial_object_base.py
chipscopy/api/ibert/tx.py
chipscopy/api/ibert/yk_scan/__init__.py
chipscopy/api/ibert/yk_scan/manager.py
chipscopy/api/ila/__init__.py
chipscopy/api/ila/ila.py
chipscopy/api/ila/ila_capture.py
chipscopy/api/ila/ila_external_trace.py
chipscopy/api/ila/ila_external_trace_data.py
chipscopy/api/ila/ila_probe.py
chipscopy/api/ila/ila_protocol_processing.py
chipscopy/api/ila/ila_waveform.py
chipscopy/api/ila/tsm/ILATsmLexer.py
chipscopy/api/ila/tsm/ILATsmParser.py
chipscopy/api/ila/tsm/ILATsmVisitor.py
chipscopy/api/ila/tsm/__init__.py
chipscopy/api/ila/tsm/ila_tsm_checker.py
chipscopy/api/ila/tsm/ila_tsm_data.py
chipscopy/api/ila/tsm/ila_tsm_mapper.py
chipscopy/api/ila/tsm/ila_tsm_reader.py
chipscopy/api/jtag.py
chipscopy-2025.2.0.55.dist-info/LICENSE
chipscopy-2025.2.0.55.dist-info/METADATA
chipscopy-2025.2.0.55.dist-info/WHEEL
chipscopy-2025.2.0.55.dist-info/entry_points.txt
chipscopy-2025.2.0.55.dist-info/RECORD
